flask_sandbox.py
setup.py
Flask_Sandbox.egg-info/PKG-INFO
Flask_Sandbox.egg-info/SOURCES.txt
Flask_Sandbox.egg-info/dependency_links.txt
Flask_Sandbox.egg-info/not-zip-safe
Flask_Sandbox.egg-info/requires.txt
Flask_Sandbox.egg-info/top_level.txt