Metadata-Version: 1.1
Name: Flask-Sandbox
Version: 0.1.0
Summary: ACL Route controls for Flask
Home-page: https://github.com/kageurufu/flask-sandbox
Author: Frank Tackitt
Author-email: franklyn@tackitt.net
License: MIT
Platform: any
Classifier: Development Status :: 4 - Beta
Classifier: Environment :: Web Environment
Classifier: Intended Audience :: Developers
Classifier: License :: OSI Approved :: MIT License
Classifier: Operating System :: OS Independent
Classifier: Programming Language :: Python
Classifier: Topic :: Internet :: WWW/HTTP :: Dynamic Content
Classifier: Topic :: Software Development :: Libraries :: Python Modules
Classifier: Framework :: Flask
